guadania/__init__.py
guadania/guadañaFunctions.py
guadania/prisma/__init__.py
guadania/prisma/prismaEnums.py
guadania/prisma/prismaFunctions.py
guadania-1.9.10.dist-info/METADATA
guadania-1.9.10.dist-info/WHEEL
guadania-1.9.10.dist-info/top_level.txt
guadania-1.9.10.dist-info/RECORD
