Metadata-Version: 2.4
Name: guadania
Version: 1.9.10
Summary: Libreria que matará vuestro sufrimiento por la PARCA
Requires-Python: >=3.7
Requires-Dist: numpy
Requires-Dist: openpyxl
Requires-Dist: pandas
Requires-Dist: requests
Dynamic: requires-dist
Dynamic: requires-python
Dynamic: summary
